{"file:///c%3A/react_native/login_server/socketHandler.js":{"language":"JavaScript","code":98,"comment":0,"blank":9},"file:///c%3A/react_native/login_server/s3.js":{"language":"JavaScript","code":33,"comment":2,"blank":6},"file:///c%3A/react_native/login_server/package.json":{"language":"JSON","code":24,"comment":0,"blank":1},"file:///c%3A/react_native/login_server/models/User.js":{"language":"JavaScript","code":17,"comment":0,"blank":3},"file:///c%3A/react_native/login_server/models/Thread.js":{"language":"JavaScript","code":21,"comment":0,"blank":3},"file:///c%3A/react_native/login_server/models/Message.js":{"language":"JavaScript","code":15,"comment":0,"blank":3},"file:///c%3A/react_native/login_server/models/Poll.js":{"language":"JavaScript","code":32,"comment":0,"blank":3},"file:///c%3A/react_native/login_server/server.js":{"language":"JavaScript","code":1587,"comment":67,"blank":38},"file:///c%3A/react_native/login_server/models/ImagePost.js":{"language":"JavaScript","code":14,"comment":0,"blank":3},"file:///c%3A/react_native/login_server/models/Conversation.js":{"language":"JavaScript","code":22,"comment":0,"blank":3},"file:///c%3A/react_native/login_server/models/Category.js":{"language":"JavaScript","code":17,"comment":0,"blank":3},"file:///c%3A/react_native/login_server/api/Messages.js":{"language":"JavaScript","code":289,"comment":8,"blank":6},"file:///c%3A/react_native/login_server/api/User.js":{"language":"JavaScript","code":5049,"comment":262,"blank":97},"file:///c%3A/react_native/login_server/config/db.js":{"language":"JavaScript","code":11,"comment":1,"blank":1},"file:///c%3A/react_native/login_server/api/Conversations.js":{"language":"JavaScript","code":976,"comment":37,"blank":34},"file:///c%3A/react_native/login_server/.expo/README.md":{"language":"Markdown","code":9,"comment":0,"blank":9},"file:///c%3A/react_native/login_server/.expo/settings.json":{"language":"JSON with Comments","code":8,"comment":0,"blank":1}}